CHANGES.rst
CONTRIBUTORS.rst
MANIFEST.in
README.rst
buildout.cfg
setup.cfg
setup.py
travis.cfg
src/collective/__init__.py
src/collective/__init__.pyc
src/collective.api4tal.egg-info/PKG-INFO
src/collective.api4tal.egg-info/SOURCES.txt
src/collective.api4tal.egg-info/dependency_links.txt
src/collective.api4tal.egg-info/entry_points.txt
src/collective.api4tal.egg-info/namespace_packages.txt
src/collective.api4tal.egg-info/not-zip-safe
src/collective.api4tal.egg-info/requires.txt
src/collective.api4tal.egg-info/top_level.txt
src/collective/api4tal/__init__.py
src/collective/api4tal/__init__.pyc
src/collective/api4tal/configure.zcml
src/collective/api4tal/interfaces.py
src/collective/api4tal/setuphandlers.py
src/collective/api4tal/setuphandlers.pyc
src/collective/api4tal/testing.py
src/collective/api4tal/browser/__init__.py
src/collective/api4tal/browser/__init__.pyc
src/collective/api4tal/browser/api4tal.py
src/collective/api4tal/browser/api4tal.pyc
src/collective/api4tal/browser/configure.zcml
src/collective/api4tal/browser/overrides/.gitkeep
src/collective/api4tal/browser/static/.gitkeep
src/collective/api4tal/locales/collective.api4tal.pot
src/collective/api4tal/locales/update.sh
src/collective/api4tal/profiles/default/browserlayer.xml
src/collective/api4tal/profiles/default/collectiveapi4tal_default.txt
src/collective/api4tal/profiles/default/metadata.xml
src/collective/api4tal/profiles/uninstall/browserlayer.xml
src/collective/api4tal/profiles/uninstall/collectiveapi4tal_uninstall.txt
src/collective/api4tal/tests/__init__.py
src/collective/api4tal/tests/test_robot.py
src/collective/api4tal/tests/test_setup.py
src/collective/api4tal/tests/robot/test_example.robot