Metadata-Version: 1.1
Name: collective.api4tal
Version: 0.1
Summary: Plone.api for TAL, use in pt file
Home-page: http://pypi.python.org/pypi/collective.api4tal
Author: andy fang
Author-email: andy@mingtak.com.tw
License: GPL version 2
Keywords: Python Plone
Platform: UNKNOWN
Classifier: Environment :: Web Environment
Classifier: Framework :: Plone
Classifier: Framework :: Plone :: 5.0
Classifier: Programming Language :: Python
Classifier: Programming Language :: Python :: 2.7
Classifier: Operating System :: OS Independent
Classifier: License :: OSI Approved :: GNU General Public License v2 (GPLv2)
